{
  "ID": "7f62702e-5ebb-4e30-8d99-b323667d7043",
  "Version": "3.10.0.0",
  "Name": "LobbyScene",
  "Content": {
    "Content": {
      "Animation": {
        "Duration": 0,
        "Speed": 1.0,
        "Timelines": [],
        "ctype": "TimelineActionData"
      },
      "AnimationList": [],
      "ObjectData": {
        "Tag": 380,
        "Children": [
          {
            "FileData": {
              "Type": "Normal",
              "Path": "Image/Lobby/bg.png",
              "Plist": ""
            },
            "Scale9OriginX": 211,
            "Scale9OriginY": 118,
            "Scale9Width": 218,
            "Scale9Height": 124,
            "AnchorPoint": {
              "ScaleX": 0.5,
              "ScaleY": 0.5
            },
            "Position": {
              "X": 640.0,
              "Y": 360.0
            },
            "Scale": {
              "ScaleX": 2.0,
              "ScaleY": 2.0
            },
            "CColor": {},
            "IconVisible": false,
            "PrePosition": {
              "X": 0.5,
              "Y": 0.5
            },
            "PreSize": {
              "X": 0.5,
              "Y": 0.5
            },
            "LeftMargin": 320.0,
            "RightMargin": 320.0,
            "TopMargin": 180.0,
            "BottomMargin": 180.0,
            "Tag": 12,
            "ActionTag": 1652530875,
            "Size": {
              "X": 640.0,
              "Y": 360.0
            },
            "Name": "Bg",
            "ctype": "ImageViewObjectData"
          },
          {
            "FileData": {
              "Type": "Normal",
              "Path": "Image/Lobby/tian.png",
              "Plist": ""
            },
            "Scale9OriginX": 101,
            "Scale9OriginY": 27,
            "Scale9Width": 106,
            "Scale9Height": 30,
            "AnchorPoint": {
              "ScaleX": 0.5,
              "ScaleY": 0.5
            },
            "Position": {
              "X": 664.6146,
              "Y": 635.8957
            },
            "Scale": {
              "ScaleX": 2.0,
              "ScaleY": 2.0
            },
            "CColor": {},
            "IconVisible": false,
            "PrePosition": {
              "X": 0.5192,
              "Y": 0.8832
            },
            "PreSize": {
              "X": 0.2406,
              "Y": 0.1167
            },
            "LeftMargin": 510.6146,
            "RightMargin": 461.3854,
            "TopMargin": 42.1043,
            "BottomMargin": 593.8957,
            "Tag": 13,
            "ActionTag": -1018483150,
            "Size": {
              "X": 308.0,
              "Y": 84.0
            },
            "Name": "title",
            "ctype": "ImageViewObjectData"
          },
          {
            "AnchorPoint": {},
            "Position": {
              "X": 0.0,
              "Y": 0.0
            },
            "Scale": {
              "ScaleX": 1.0,
              "ScaleY": 1.0
            },
            "CColor": {},
            "IconVisible": true,
            "PrePosition": {
              "X": 0.0,
              "Y": 0.0
            },
            "PreSize": {
              "X": 0.0,
              "Y": 0.0
            },
            "RightMargin": 1280.0,
            "TopMargin": 720.0,
            "Tag": 35,
            "Children": [
              {
                "FileData": {
                  "Type": "Normal",
                  "Path": "Image/Lobby/zs.png",
                  "Plist": ""
                },
                "Scale9OriginX": 6,
                "Scale9OriginY": 6,
                "Scale9Width": 8,
                "Scale9Height": 7,
                "AnchorPoint": {
                  "ScaleX": 0.5,
                  "ScaleY": 0.5
                },
                "Position": {
                  "X": 42.6638,
                  "Y": 568.8704
                },
                "Scale": {
                  "ScaleX": 2.0,
                  "ScaleY": 2.0
                },
                "CColor": {},
                "IconVisible": false,
                "PrePosition": {
                  "X": 0.0,
                  "Y": 0.0
                },
                "PreSize": {
                  "X": 0.0,
                  "Y": 0.0
                },
                "LeftMargin": 32.6638,
                "RightMargin": -52.6638,
                "TopMargin": -578.3704,
                "BottomMargin": 559.3704,
                "Tag": 34,
                "ActionTag": 1625588792,
                "Size": {
                  "X": 20.0,
                  "Y": 19.0
                },
                "Name": "icon",
                "ctype": "ImageViewObjectData"
              },
              {
                "FontSize": 30,
                "LabelText": "x999",
                "OutlineColor": {
                  "G": 0,
                  "B": 0
                },
                "ShadowColor": {
                  "R": 110,
                  "G": 110,
                  "B": 110
                },
                "ShadowOffsetX": 2.0,
                "ShadowOffsetY": -2.0,
                "AnchorPoint": {
                  "ScaleY": 0.5
                },
                "Position": {
                  "X": 78.4605,
                  "Y": 568.8788
                },
                "Scale": {
                  "ScaleX": 1.0,
                  "ScaleY": 1.0
                },
                "CColor": {},
                "IconVisible": false,
                "PrePosition": {
                  "X": 0.0,
                  "Y": 0.0
                },
                "PreSize": {
                  "X": 0.0,
                  "Y": 0.0
                },
                "LeftMargin": 78.4605,
                "RightMargin": -144.4605,
                "TopMargin": -585.8788,
                "BottomMargin": 551.8788,
                "Tag": 36,
                "ActionTag": -1282599122,
                "Size": {
                  "X": 66.0,
                  "Y": 34.0
                },
                "Name": "DiamondCount",
                "ctype": "TextObjectData"
              }
            ],
            "ActionTag": 675422935,
            "Size": {
              "X": 0.0,
              "Y": 0.0
            },
            "Name": "DiamondNode",
            "ctype": "SingleNodeObjectData"
          },
          {
            "FileData": {
              "Type": "Normal",
              "Path": "Image/Lobby/g.png",
              "Plist": ""
            },
            "Scale9OriginX": 66,
            "Scale9OriginY": 89,
            "Scale9Width": 70,
            "Scale9Height": 94,
            "AnchorPoint": {
              "ScaleX": 0.5,
              "ScaleY": 0.5
            },
            "Position": {
              "X": 717.9476,
              "Y": 276.9233
            },
            "Scale": {
              "ScaleX": 2.0,
              "ScaleY": 2.0
            },
            "CColor": {},
            "IconVisible": false,
            "PrePosition": {
              "X": 0.5609,
              "Y": 0.3846
            },
            "PreSize": {
              "X": 0.1578,
              "Y": 0.3778
            },
            "LeftMargin": 616.9476,
            "RightMargin": 461.0524,
            "TopMargin": 307.0767,
            "BottomMargin": 140.9233,
            "Tag": 14,
            "Children": [
              {
                "FileData": {
                  "Type": "Normal",
                  "Path": "Image/Lobby/xin.png",
                  "Plist": ""
                },
                "Scale9OriginX": 13,
                "Scale9OriginY": 14,
                "Scale9Width": 14,
                "Scale9Height": 15,
                "AnchorPoint": {
                  "ScaleX": 0.5,
                  "ScaleY": 0.5
                },
                "Position": {
                  "X": 168.2075,
                  "Y": 183.5901
                },
                "Scale": {
                  "ScaleX": 1.0,
                  "ScaleY": 1.0
                },
                "CColor": {},
                "IconVisible": false,
                "PrePosition": {
                  "X": 0.8327,
                  "Y": 0.675
                },
                "PreSize": {
                  "X": 0.198,
                  "Y": 0.1581
                },
                "LeftMargin": 148.2075,
                "RightMargin": 13.7925,
                "TopMargin": 66.9099,
                "BottomMargin": 162.0901,
                "Tag": 15,
                "ActionTag": 2031498745,
                "Size": {
                  "X": 40.0,
                  "Y": 43.0
                },
                "Name": "puke",
                "ctype": "ImageViewObjectData"
              }
            ],
            "ActionTag": -1673652862,
            "Size": {
              "X": 202.0,
              "Y": 272.0
            },
            "Name": "g",
            "ctype": "ImageViewObjectData"
          },
          {
            "AnchorPoint": {},
            "Position": {
              "X": 58.5634,
              "Y": 665.9809
            },
            "Scale": {
              "ScaleX": 1.0,
              "ScaleY": 1.0
            },
            "CColor": {},
            "IconVisible": true,
            "PrePosition": {
              "X": 0.0458,
              "Y": 0.925
            },
            "PreSize": {
              "X": 0.0,
              "Y": 0.0
            },
            "LeftMargin": 58.5634,
            "RightMargin": 1221.4365,
            "TopMargin": 54.0191,
            "BottomMargin": 665.9809,
            "Tag": 16,
            "Children": [
              {
                "FileData": {
                  "Type": "Normal",
                  "Path": "Image/Lobby/tx.png",
                  "Plist": ""
                },
                "Scale9OriginX": 15,
                "Scale9OriginY": 15,
                "Scale9Width": 17,
                "Scale9Height": 16,
                "AnchorPoint": {
                  "ScaleX": 0.5,
                  "ScaleY": 0.5
                },
                "Position": {
                  "X": 0.0,
                  "Y": 0.0
                },
                "Scale": {
                  "ScaleX": 2.0,
                  "ScaleY": 2.0
                },
                "CColor": {},
                "IconVisible": false,
                "PrePosition": {
                  "X": 0.0,
                  "Y": 0.0
                },
                "PreSize": {
                  "X": 0.0,
                  "Y": 0.0
                },
                "LeftMargin": -23.5,
                "RightMargin": -23.5,
                "TopMargin": -23.0,
                "BottomMargin": -23.0,
                "Tag": 17,
                "ActionTag": -1732500855,
                "Size": {
                  "X": 47.0,
                  "Y": 46.0
                },
                "Name": "headIcon_bg",
                "ctype": "ImageViewObjectData"
              },
              {
                "FileData": {
                  "Type": "Normal",
                  "Path": "Image/Lobby/name_bg.png",
                  "Plist": ""
                },
                "Scale9OriginX": 30,
                "Scale9OriginY": 8,
                "Scale9Width": 33,
                "Scale9Height": 9,
                "AnchorPoint": {
                  "ScaleX": 0.5,
                  "ScaleY": 0.5
                },
                "Position": {
                  "X": 153.846,
                  "Y": 14.3593
                },
                "Scale": {
                  "ScaleX": 2.0,
                  "ScaleY": 2.0
                },
                "CColor": {},
                "IconVisible": false,
                "PrePosition": {
                  "X": 0.0,
                  "Y": 0.0
                },
                "PreSize": {
                  "X": 0.0,
                  "Y": 0.0
                },
                "LeftMargin": 107.346,
                "RightMargin": -200.346,
                "TopMargin": -26.8593,
                "BottomMargin": 1.8593,
                "Tag": 18,
                "ActionTag": -1465204545,
                "Size": {
                  "X": 93.0,
                  "Y": 25.0
                },
                "Name": "name_bg",
                "ctype": "ImageViewObjectData"
              },
              {
                "FontSize": 30,
                "LabelText": "ID:",
                "OutlineColor": {
                  "G": 0,
                  "B": 0
                },
                "ShadowColor": {
                  "R": 110,
                  "G": 110,
                  "B": 110
                },
                "ShadowOffsetX": 2.0,
                "ShadowOffsetY": -2.0,
                "AnchorPoint": {
                  "ScaleX": 0.5,
                  "ScaleY": 0.5
                },
                "Position": {
                  "X": 85.5535,
                  "Y": -31.5196
                },
                "Scale": {
                  "ScaleX": 1.0,
                  "ScaleY": 1.0
                },
                "CColor": {},
                "IconVisible": false,
                "PrePosition": {
                  "X": 0.0,
                  "Y": 0.0
                },
                "PreSize": {
                  "X": 0.0,
                  "Y": 0.0
                },
                "LeftMargin": 66.0535,
                "RightMargin": -105.0535,
                "TopMargin": 14.5196,
                "BottomMargin": -48.5196,
                "Tag": 20,
                "ActionTag": 1181204586,
                "Size": {
                  "X": 39.0,
                  "Y": 34.0
                },
                "Name": "Text",
                "ctype": "TextObjectData"
              },
              {
                "FontSize": 30,
                "LabelText": "123456",
                "OutlineColor": {
                  "G": 0,
                  "B": 0
                },
                "ShadowColor": {
                  "R": 110,
                  "G": 110,
                  "B": 110
                },
                "ShadowOffsetX": 2.0,
                "ShadowOffsetY": -2.0,
                "AnchorPoint": {
                  "ScaleY": 0.5
                },
                "Position": {
                  "X": 112.5132,
                  "Y": -32.4194
                },
                "Scale": {
                  "ScaleX": 1.0,
                  "ScaleY": 1.0
                },
                "CColor": {},
                "IconVisible": false,
                "PrePosition": {
                  "X": 0.0,
                  "Y": 0.0
                },
                "PreSize": {
                  "X": 0.0,
                  "Y": 0.0
                },
                "LeftMargin": 112.5132,
                "RightMargin": -213.5132,
                "TopMargin": 15.4194,
                "BottomMargin": -49.4194,
                "Tag": 21,
                "ActionTag": -1097403497,
                "Size": {
                  "X": 101.0,
                  "Y": 34.0
                },
                "Name": "TextId",
                "ctype": "TextObjectData"
              },
              {
                "FontSize": 30,
                "LabelText": "name",
                "OutlineColor": {
                  "G": 0,
                  "B": 0
                },
                "ShadowColor": {
                  "R": 110,
                  "G": 110,
                  "B": 110
                },
                "ShadowOffsetX": 2.0,
                "ShadowOffsetY": -2.0,
                "AnchorPoint": {
                  "ScaleX": 0.5,
                  "ScaleY": 0.5
                },
                "Position": {
                  "X": 170.3116,
                  "Y": 12.5153
                },
                "Scale": {
                  "ScaleX": 1.0,
                  "ScaleY": 1.0
                },
                "CColor": {},
                "IconVisible": false,
                "PrePosition": {
                  "X": 0.0,
                  "Y": 0.0
                },
                "PreSize": {
                  "X": 0.0,
                  "Y": 0.0
                },
                "LeftMargin": 132.3116,
                "RightMargin": -208.3116,
                "TopMargin": -29.5153,
                "BottomMargin": -4.4847,
                "Tag": 22,
                "ActionTag": -1440380386,
                "Size": {
                  "X": 76.0,
                  "Y": 34.0
                },
                "VisibleForFrame": false,
                "Name": "TextName",
                "ctype": "TextObjectData"
              }
            ],
            "ActionTag": 603294761,
            "Size": {
              "X": 0.0,
              "Y": 0.0
            },
            "Name": "touxiang",
            "ctype": "SingleNodeObjectData"
          },
          {
            "AnchorPoint": {},
            "Position": {
              "X": 0.0,
              "Y": 0.0
            },
            "Scale": {
              "ScaleX": 1.0,
              "ScaleY": 1.0
            },
            "CColor": {},
            "IconVisible": true,
            "PrePosition": {
              "X": 0.0,
              "Y": 0.0
            },
            "PreSize": {
              "X": 0.0,
              "Y": 0.0
            },
            "RightMargin": 1280.0,
            "TopMargin": 720.0,
            "Tag": 37,
            "Children": [
              {
                "FontSize": 14,
                "ButtonText": "",
                "TextColor": {
                  "R": 65,
                  "G": 65,
                  "B": 70
                },
                "DisabledFileData": {
                  "Type": "Default",
                  "Path": "Default/Button_Disable.png",
                  "Plist": ""
                },
                "PressedFileData": {
                  "Type": "Normal",
                  "Path": "Image/Lobby/cjfj.png",
                  "Plist": ""
                },
                "NormalFileData": {
                  "Type": "Normal",
                  "Path": "Image/Lobby/cjfj.png",
                  "Plist": ""
                },
                "Scale9OriginX": 15,
                "Scale9OriginY": 11,
                "Scale9Width": 123,
                "Scale9Height": 40,
                "OutlineColor": {
                  "G": 0,
                  "B": 0
                },
                "ShadowColor": {
                  "R": 110,
                  "G": 110,
                  "B": 110
                },
                "ShadowOffsetX": 2.0,
                "ShadowOffsetY": -2.0,
                "TouchEnable": true,
                "AnchorPoint": {
                  "ScaleX": 0.5,
                  "ScaleY": 0.5
                },
                "Position": {
                  "X": 1083.95,
                  "Y": 458.8992
                },
                "Scale": {
                  "ScaleX": 2.0,
                  "ScaleY": 2.0
                },
                "CColor": {},
                "IconVisible": false,
                "PrePosition": {
                  "X": 0.0,
                  "Y": 0.0
                },
                "PreSize": {
                  "X": 0.0,
                  "Y": 0.0
                },
                "LeftMargin": 1007.45,
                "RightMargin": -1160.45,
                "TopMargin": -489.8992,
                "BottomMargin": 427.8992,
                "Tag": 23,
                "ActionTag": -1629248570,
                "Size": {
                  "X": 153.0,
                  "Y": 62.0
                },
                "Name": "Btn_create_room",
                "ctype": "ButtonObjectData"
              },
              {
                "FontSize": 14,
                "ButtonText": "",
                "TextColor": {
                  "R": 65,
                  "G": 65,
                  "B": 70
                },
                "DisabledFileData": {
                  "Type": "Default",
                  "Path": "Default/Button_Disable.png",
                  "Plist": ""
                },
                "PressedFileData": {
                  "Type": "Normal",
                  "Path": "Image/Lobby/jrfj.png",
                  "Plist": ""
                },
                "NormalFileData": {
                  "Type": "Normal",
                  "Path": "Image/Lobby/jrfj.png",
                  "Plist": ""
                },
                "Scale9OriginX": 15,
                "Scale9OriginY": 11,
                "Scale9Width": 123,
                "Scale9Height": 40,
                "OutlineColor": {
                  "G": 0,
                  "B": 0
                },
                "ShadowColor": {
                  "R": 110,
                  "G": 110,
                  "B": 110
                },
                "ShadowOffsetX": 2.0,
                "ShadowOffsetY": -2.0,
                "TouchEnable": true,
                "AnchorPoint": {
                  "ScaleX": 0.5,
                  "ScaleY": 0.5
                },
                "Position": {
                  "X": 1088.6754,
                  "Y": 317.0315
                },
                "Scale": {
                  "ScaleX": 2.0,
                  "ScaleY": 2.0
                },
                "CColor": {},
                "IconVisible": false,
                "PrePosition": {
                  "X": 0.0,
                  "Y": 0.0
                },
                "PreSize": {
                  "X": 0.0,
                  "Y": 0.0
                },
                "LeftMargin": 1012.1754,
                "RightMargin": -1165.1754,
                "TopMargin": -348.0315,
                "BottomMargin": 286.0315,
                "Tag": 24,
                "ActionTag": 1047882093,
                "Size": {
                  "X": 153.0,
                  "Y": 62.0
                },
                "Name": "Btn_join_room",
                "ctype": "ButtonObjectData"
              },
              {
                "FontSize": 14,
                "ButtonText": "",
                "TextColor": {
                  "R": 65,
                  "G": 65,
                  "B": 70
                },
                "DisabledFileData": {
                  "Type": "Default",
                  "Path": "Default/Button_Disable.png",
                  "Plist": ""
                },
                "PressedFileData": {
                  "Type": "Normal",
                  "Path": "Image/Lobby/jlb.png",
                  "Plist": ""
                },
                "NormalFileData": {
                  "Type": "Normal",
                  "Path": "Image/Lobby/jlb.png",
                  "Plist": ""
                },
                "Scale9OriginX": 15,
                "Scale9OriginY": 11,
                "Scale9Width": 125,
                "Scale9Height": 40,
                "OutlineColor": {
                  "G": 0,
                  "B": 0
                },
                "ShadowColor": {
                  "R": 110,
                  "G": 110,
                  "B": 110
                },
                "ShadowOffsetX": 2.0,
                "ShadowOffsetY": -2.0,
                "TouchEnable": true,
                "AnchorPoint": {
                  "ScaleX": 0.5,
                  "ScaleY": 0.5
                },
                "Position": {
                  "X": 1082.8499,
                  "Y": 169.889
                },
                "Scale": {
                  "ScaleX": 2.0,
                  "ScaleY": 2.0
                },
                "CColor": {},
                "IconVisible": false,
                "PrePosition": {
                  "X": 0.0,
                  "Y": 0.0
                },
                "PreSize": {
                  "X": 0.0,
                  "Y": 0.0
                },
                "LeftMargin": 1005.3499,
                "RightMargin": -1160.3499,
                "TopMargin": -200.889,
                "BottomMargin": 138.889,
                "Tag": 25,
                "ActionTag": -1410176929,
                "Size": {
                  "X": 155.0,
                  "Y": 62.0
                },
                "Name": "Btn_Club",
                "ctype": "ButtonObjectData"
              },
              {
                "FontSize": 14,
                "ButtonText": "",
                "TextColor": {
                  "R": 65,
                  "G": 65,
                  "B": 70
                },
                "DisabledFileData": {
                  "Type": "Default",
                  "Path": "Default/Button_Disable.png",
                  "Plist": ""
                },
                "PressedFileData": {
                  "Type": "Normal",
                  "Path": "Image/Lobby/shiminngrenzheng.png",
                  "Plist": ""
                },
                "NormalFileData": {
                  "Type": "Normal",
                  "Path": "Image/Lobby/shiminngrenzheng.png",
                  "Plist": ""
                },
                "Scale9OriginX": 15,
                "Scale9OriginY": 11,
                "Scale9Width": 9,
                "Scale9Height": 15,
                "OutlineColor": {
                  "G": 0,
                  "B": 0
                },
                "ShadowColor": {
                  "R": 110,
                  "G": 110,
                  "B": 110
                },
                "ShadowOffsetX": 2.0,
                "ShadowOffsetY": -2.0,
                "TouchEnable": true,
                "AnchorPoint": {
                  "ScaleX": 0.5,
                  "ScaleY": 0.5
                },
                "Position": {
                  "X": 1190.4318,
                  "Y": 568.6783
                },
                "Scale": {
                  "ScaleX": 2.0,
                  "ScaleY": 2.0
                },
                "CColor": {},
                "IconVisible": false,
                "PrePosition": {
                  "X": 0.0,
                  "Y": 0.0
                },
                "PreSize": {
                  "X": 0.0,
                  "Y": 0.0
                },
                "LeftMargin": 1170.9318,
                "RightMargin": -1209.9318,
                "TopMargin": -587.1783,
                "BottomMargin": 550.1783,
                "Tag": 27,
                "ActionTag": 2331202,
                "Size": {
                  "X": 39.0,
                  "Y": 37.0
                },
                "Name": "Btn_Renzheng",
                "ctype": "ButtonObjectData"
              },
              {
                "FontSize": 14,
                "ButtonText": "",
                "TextColor": {
                  "R": 65,
                  "G": 65,
                  "B": 70
                },
                "DisabledFileData": {
                  "Type": "Default",
                  "Path": "Default/Button_Disable.png",
                  "Plist": ""
                },
                "PressedFileData": {
                  "Type": "Normal",
                  "Path": "Image/Lobby/shangcheng.png",
                  "Plist": ""
                },
                "NormalFileData": {
                  "Type": "Normal",
                  "Path": "Image/Lobby/shangcheng.png",
                  "Plist": ""
                },
                "Scale9OriginX": 15,
                "Scale9OriginY": 11,
                "Scale9Width": 72,
                "Scale9Height": 19,
                "OutlineColor": {
                  "G": 0,
                  "B": 0
                },
                "ShadowColor": {
                  "R": 110,
                  "G": 110,
                  "B": 110
                },
                "ShadowOffsetX": 2.0,
                "ShadowOffsetY": -2.0,
                "TouchEnable": true,
                "AnchorPoint": {
                  "ScaleX": 0.5,
                  "ScaleY": 0.5
                },
                "Position": {
                  "X": 1164.0615,
                  "Y": 663.6234
                },
                "Scale": {
                  "ScaleX": 2.0,
                  "ScaleY": 2.0
                },
                "CColor": {},
                "IconVisible": false,
                "PrePosition": {
                  "X": 0.0,
                  "Y": 0.0
                },
                "PreSize": {
                  "X": 0.0,
                  "Y": 0.0
                },
                "LeftMargin": 1113.0615,
                "RightMargin": -1215.0615,
                "TopMargin": -684.1234,
                "BottomMargin": 643.1234,
                "Tag": 28,
                "ActionTag": -394637531,
                "Size": {
                  "X": 102.0,
                  "Y": 41.0
                },
                "Name": "Btn_Shop",
                "ctype": "ButtonObjectData"
              },
              {
                "FontSize": 14,
                "ButtonText": "",
                "TextColor": {
                  "R": 65,
                  "G": 65,
                  "B": 70
                },
                "DisabledFileData": {
                  "Type": "Default",
                  "Path": "Default/Button_Disable.png",
                  "Plist": ""
                },
                "PressedFileData": {
                  "Type": "Normal",
                  "Path": "Image/Lobby/zj.png",
                  "Plist": ""
                },
                "NormalFileData": {
                  "Type": "Normal",
                  "Path": "Image/Lobby/zj.png",
                  "Plist": ""
                },
                "Scale9OriginX": 15,
                "Scale9OriginY": 11,
                "Scale9Width": 34,
                "Scale9Height": 3,
                "OutlineColor": {
                  "G": 0,
                  "B": 0
                },
                "ShadowColor": {
                  "R": 110,
                  "G": 110,
                  "B": 110
                },
                "ShadowOffsetX": 2.0,
                "ShadowOffsetY": -2.0,
                "TouchEnable": true,
                "AnchorPoint": {
                  "ScaleX": 0.5,
                  "ScaleY": 0.5
                },
                "Position": {
                  "X": 269.4484,
                  "Y": 49.6693
                },
                "Scale": {
                  "ScaleX": 2.0,
                  "ScaleY": 2.0
                },
                "CColor": {},
                "IconVisible": false,
                "PrePosition": {
                  "X": 0.0,
                  "Y": 0.0
                },
                "PreSize": {
                  "X": 0.0,
                  "Y": 0.0
                },
                "LeftMargin": 237.4484,
                "RightMargin": -301.4484,
                "TopMargin": -62.1693,
                "BottomMargin": 37.1693,
                "Tag": 29,
                "ActionTag": 1351042583,
                "Size": {
                  "X": 64.0,
                  "Y": 25.0
                },
                "Name": "Btn_Record",
                "ctype": "ButtonObjectData"
              },
              {
                "FontSize": 14,
                "ButtonText": "",
                "TextColor": {
                  "R": 65,
                  "G": 65,
                  "B": 70
                },
                "DisabledFileData": {
                  "Type": "Default",
                  "Path": "Default/Button_Disable.png",
                  "Plist": ""
                },
                "PressedFileData": {
                  "Type": "Normal",
                  "Path": "Image/Lobby/xx.png",
                  "Plist": ""
                },
                "NormalFileData": {
                  "Type": "Normal",
                  "Path": "Image/Lobby/xx.png",
                  "Plist": ""
                },
                "Scale9OriginX": 15,
                "Scale9OriginY": 11,
                "Scale9Width": 37,
                "Scale9Height": 5,
                "OutlineColor": {
                  "G": 0,
                  "B": 0
                },
                "ShadowColor": {
                  "R": 110,
                  "G": 110,
                  "B": 110
                },
                "ShadowOffsetX": 2.0,
                "ShadowOffsetY": -2.0,
                "TouchEnable": true,
                "AnchorPoint": {
                  "ScaleX": 0.5,
                  "ScaleY": 0.5
                },
                "Position": {
                  "X": 443.5131,
                  "Y": 57.5812
                },
                "Scale": {
                  "ScaleX": 2.0,
                  "ScaleY": 2.0
                },
                "CColor": {},
                "IconVisible": false,
                "PrePosition": {
                  "X": 0.0,
                  "Y": 0.0
                },
                "PreSize": {
                  "X": 0.0,
                  "Y": 0.0
                },
                "LeftMargin": 410.0131,
                "RightMargin": -477.0131,
                "TopMargin": -71.0812,
                "BottomMargin": 44.0812,
                "Tag": 30,
                "ActionTag": -302241868,
                "Size": {
                  "X": 67.0,
                  "Y": 27.0
                },
                "Name": "Btn_msg",
                "ctype": "ButtonObjectData"
              },
              {
                "FontSize": 14,
                "ButtonText": "",
                "TextColor": {
                  "R": 65,
                  "G": 65,
                  "B": 70
                },
                "DisabledFileData": {
                  "Type": "Default",
                  "Path": "Default/Button_Disable.png",
                  "Plist": ""
                },
                "PressedFileData": {
                  "Type": "Normal",
                  "Path": "Image/Lobby/yqm.png",
                  "Plist": ""
                },
                "NormalFileData": {
                  "Type": "Normal",
                  "Path": "Image/Lobby/yqm.png",
                  "Plist": ""
                },
                "Scale9OriginX": 15,
                "Scale9OriginY": 5,
                "Scale9Width": 25,
                "Scale9Height": 7,
                "OutlineColor": {
                  "G": 0,
                  "B": 0
                },
                "ShadowColor": {
                  "R": 110,
                  "G": 110,
                  "B": 110
                },
                "ShadowOffsetX": 2.0,
                "ShadowOffsetY": -2.0,
                "TouchEnable": true,
                "AnchorPoint": {
                  "ScaleX": 0.5,
                  "ScaleY": 0.5
                },
                "Position": {
                  "X": 672.4131,
                  "Y": 47.5808
                },
                "Scale": {
                  "ScaleX": 2.0,
                  "ScaleY": 2.0
                },
                "CColor": {},
                "IconVisible": false,
                "PrePosition": {
                  "X": 0.0,
                  "Y": 0.0
                },
                "PreSize": {
                  "X": 0.0,
                  "Y": 0.0
                },
                "LeftMargin": 644.9131,
                "RightMargin": -699.9131,
                "TopMargin": -56.0808,
                "BottomMargin": 39.0808,
                "Tag": 31,
                "ActionTag": -1190914528,
                "Size": {
                  "X": 55.0,
                  "Y": 17.0
                },
                "Name": "Btn_yaoqing",
                "ctype": "ButtonObjectData"
              },
              {
                "FontSize": 14,
                "ButtonText": "",
                "TextColor": {
                  "R": 65,
                  "G": 65,
                  "B": 70
                },
                "DisabledFileData": {
                  "Type": "Default",
                  "Path": "Default/Button_Disable.png",
                  "Plist": ""
                },
                "PressedFileData": {
                  "Type": "Normal",
                  "Path": "Image/Lobby/fx.png",
                  "Plist": ""
                },
                "NormalFileData": {
                  "Type": "Normal",
                  "Path": "Image/Lobby/fx.png",
                  "Plist": ""
                },
                "Scale9OriginX": 15,
                "Scale9OriginY": 11,
                "Scale9Width": 40,
                "Scale9Height": 8,
                "OutlineColor": {
                  "G": 0,
                  "B": 0
                },
                "ShadowColor": {
                  "R": 110,
                  "G": 110,
                  "B": 110
                },
                "ShadowOffsetX": 2.0,
                "ShadowOffsetY": -2.0,
                "TouchEnable": true,
                "AnchorPoint": {
                  "ScaleX": 0.5,
                  "ScaleY": 0.5
                },
                "Position": {
                  "X": 838.5657,
                  "Y": 55.4928
                },
                "Scale": {
                  "ScaleX": 2.0,
                  "ScaleY": 2.0
                },
                "CColor": {},
                "IconVisible": false,
                "PrePosition": {
                  "X": 0.0,
                  "Y": 0.0
                },
                "PreSize": {
                  "X": 0.0,
                  "Y": 0.0
                },
                "LeftMargin": 803.5657,
                "RightMargin": -873.5657,
                "TopMargin": -70.4928,
                "BottomMargin": 40.4928,
                "Tag": 32,
                "ActionTag": 1919310876,
                "Size": {
                  "X": 70.0,
                  "Y": 30.0
                },
                "Name": "Btn_Share",
                "ctype": "ButtonObjectData"
              },
              {
                "FontSize": 14,
                "ButtonText": "",
                "TextColor": {
                  "R": 65,
                  "G": 65,
                  "B": 70
                },
                "DisabledFileData": {
                  "Type": "Default",
                  "Path": "Default/Button_Disable.png",
                  "Plist": ""
                },
                "PressedFileData": {
                  "Type": "Normal",
                  "Path": "Image/Lobby/cd.png",
                  "Plist": ""
                },
                "NormalFileData": {
                  "Type": "Normal",
                  "Path": "Image/Lobby/cd.png",
                  "Plist": ""
                },
                "Scale9OriginX": 15,
                "Scale9OriginY": 11,
                "Scale9Width": 39,
                "Scale9Height": 9,
                "OutlineColor": {
                  "G": 0,
                  "B": 0
                },
                "ShadowColor": {
                  "R": 110,
                  "G": 110,
                  "B": 110
                },
                "ShadowOffsetX": 2.0,
                "ShadowOffsetY": -2.0,
                "TouchEnable": true,
                "AnchorPoint": {
                  "ScaleX": 0.5,
                  "ScaleY": 0.5
                },
                "Position": {
                  "X": 1017.9053,
                  "Y": 58.1301
                },
                "Scale": {
                  "ScaleX": 2.0,
                  "ScaleY": 2.0
                },
                "CColor": {},
                "IconVisible": false,
                "PrePosition": {
                  "X": 0.0,
                  "Y": 0.0
                },
                "PreSize": {
                  "X": 0.0,
                  "Y": 0.0
                },
                "LeftMargin": 983.4053,
                "RightMargin": -1052.4053,
                "TopMargin": -73.6301,
                "BottomMargin": 42.6301,
                "Tag": 33,
                "ActionTag": -2066185992,
                "Size": {
                  "X": 69.0,
                  "Y": 31.0
                },
                "Name": "Btn_Menu",
                "ctype": "ButtonObjectData"
              }
            ],
            "ActionTag": -1520225812,
            "Size": {
              "X": 0.0,
              "Y": 0.0
            },
            "Name": "BtnsNode",
            "ctype": "SingleNodeObjectData"
          },
          {
            "AnchorPoint": {},
            "Position": {
              "X": 0.0,
              "Y": 0.0
            },
            "Scale": {
              "ScaleX": 1.0,
              "ScaleY": 1.0
            },
            "CColor": {},
            "IconVisible": true,
            "PrePosition": {
              "X": 0.0,
              "Y": 0.0
            },
            "PreSize": {
              "X": 0.0,
              "Y": 0.0
            },
            "RightMargin": 1280.0,
            "TopMargin": 720.0,
            "Tag": 38,
            "Children": [
              {
                "FontSize": 14,
                "ButtonText": "",
                "TextColor": {
                  "R": 65,
                  "G": 65,
                  "B": 70
                },
                "DisabledFileData": {
                  "Type": "Default",
                  "Path": "Default/Button_Disable.png",
                  "Plist": ""
                },
                "PressedFileData": {
                  "Type": "Normal",
                  "Path": "Image/Lobby/jh.png",
                  "Plist": ""
                },
                "NormalFileData": {
                  "Type": "Normal",
                  "Path": "Image/Lobby/jh.png",
                  "Plist": ""
                },
                "Scale9Enable": true,
                "Scale9OriginX": 15,
                "Scale9OriginY": 11,
                "Scale9Width": 14,
                "Scale9Height": 22,
                "OutlineColor": {
                  "G": 0,
                  "B": 0
                },
                "ShadowColor": {
                  "R": 110,
                  "G": 110,
                  "B": 110
                },
                "ShadowOffsetX": 2.0,
                "ShadowOffsetY": -2.0,
                "TouchEnable": true,
                "AnchorPoint": {
                  "ScaleX": 0.5,
                  "ScaleY": 0.5
                },
                "Position": {
                  "X": 272.5916,
                  "Y": 329.4788
                },
                "Scale": {
                  "ScaleX": 2.0,
                  "ScaleY": 2.0
                },
                "CColor": {},
                "IconVisible": false,
                "PrePosition": {
                  "X": 0.0,
                  "Y": 0.0
                },
                "PreSize": {
                  "X": 0.0,
                  "Y": 0.0
                },
                "LeftMargin": 250.5916,
                "RightMargin": -294.5916,
                "TopMargin": -351.4788,
                "BottomMargin": 307.4788,
                "Tag": 39,
                "ActionTag": -412670101,
                "Size": {
                  "X": 44.0,
                  "Y": 44.0
                },
                "Name": "Btn_RreateRoom",
                "ctype": "ButtonObjectData"
              },
              {
                "FileData": {
                  "Type": "Normal",
                  "Path": "Image/Lobby/t1.png",
                  "Plist": ""
                },
                "Scale9OriginX": 44,
                "Scale9OriginY": 12,
                "Scale9Width": 46,
                "Scale9Height": 15,
                "AnchorPoint": {
                  "ScaleX": 0.5,
                  "ScaleY": 0.5
                },
                "Position": {
                  "X": 269.0349,
                  "Y": 220.4433
                },
                "Scale": {
                  "ScaleX": 2.0,
                  "ScaleY": 2.0
                },
                "CColor": {},
                "IconVisible": false,
                "PrePosition": {
                  "X": 0.0,
                  "Y": 0.0
                },
                "PreSize": {
                  "X": 0.0,
                  "Y": 0.0
                },
                "LeftMargin": 202.0349,
                "RightMargin": -336.0349,
                "TopMargin": -239.9433,
                "BottomMargin": 200.9433,
                "Tag": 41,
                "ActionTag": 171550211,
                "Size": {
                  "X": 134.0,
                  "Y": 39.0
                },
                "Name": "Image_16",
                "ctype": "ImageViewObjectData"
              }
            ],
            "ActionTag": 1130885332,
            "Size": {
              "X": 0.0,
              "Y": 0.0
            },
            "Name": "RoomListNode",
            "ctype": "SingleNodeObjectData"
          }
        ],
        "Size": {
          "X": 1280.0,
          "Y": 720.0
        },
        "Name": "Scene",
        "ctype": "SingleNodeObjectData"
      },
      "UsedResources": [
        "../Default/Button_Disable.png",
        "../Image/Lobby/bg.png",
        "../Image/Lobby/cd.png",
        "../Image/Lobby/cjfj.png",
        "../Image/Lobby/fx.png",
        "../Image/Lobby/g.png",
        "../Image/Lobby/jh.png",
        "../Image/Lobby/jlb.png",
        "../Image/Lobby/jrfj.png",
        "../Image/Lobby/name_bg.png",
        "../Image/Lobby/shangcheng.png",
        "../Image/Lobby/shiminngrenzheng.png",
        "../Image/Lobby/t1.png",
        "../Image/Lobby/tian.png",
        "../Image/Lobby/tx.png",
        "../Image/Lobby/xin.png",
        "../Image/Lobby/xx.png",
        "../Image/Lobby/yqm.png",
        "../Image/Lobby/zj.png",
        "../Image/Lobby/zs.png"
      ],
      "ctype": "GameFileData"
    }
  },
  "Type": "Scene"
}